README.md
setup.cfg
setup.py
lru_redis_cache/__init__.py
lru_redis_cache/cache_manager.py
lru_redis_cache/redis_manager.py
lru_redis_cache.egg-info/PKG-INFO
lru_redis_cache.egg-info/SOURCES.txt
lru_redis_cache.egg-info/dependency_links.txt
lru_redis_cache.egg-info/requires.txt
lru_redis_cache.egg-info/top_level.txt