Metadata-Version: 2.1
Name: lru-redis-cache
Version: 0.1
Summary: LRU Cache for Python using Redis
Home-page: https://github.com/estebansolo/david_solorzano_test/tree/master/question_c
Author: Esteban Solorzano
Author-email: estebansolorzano27@gmail.com
License: MIT
Keywords: LRU,Cache,Redis
Platform: UNKNOWN
Classifier: Intended Audience :: Developers
Classifier: Topic :: Software Development :: Build Tools
Classifier: License :: OSI Approved :: MIT License
Classifier: Programming Language :: Python :: 3.5
Classifier: Programming Language :: Python :: 3.6
Classifier: Programming Language :: Python :: 3.7
